zensols/dltools/__init__.py
zensols/dltools/conv.py
zensols/dltools/cuda_conf.py
zensols/dltools/linear.py
zensols/dltools/plot.py
zensols.dltools-0.0.3.dist-info/LICENSE.txt
zensols.dltools-0.0.3.dist-info/METADATA
zensols.dltools-0.0.3.dist-info/WHEEL
zensols.dltools-0.0.3.dist-info/entry_points.txt
zensols.dltools-0.0.3.dist-info/top_level.txt
zensols.dltools-0.0.3.dist-info/RECORD
