Metadata-Version: 2.1
Name: zensols.dltools
Version: 0.0.3
Summary: General deep learing utility library
Home-page: https://github.com/plandes/dltools
Author: Paul Landes
Author-email: landes@mailc.net
License: UNKNOWN
Download-URL: https://github.com/plandes/dltools/releases/download/v0.0.3/zensols.dltools-0.0.3-py3-none-any.whl
Keywords: tooling
Platform: UNKNOWN
Requires-Dist: scipy (==1.3.1)
Requires-Dist: matplotlib (==3.1.1)
Requires-Dist: numpy (==1.17.2)
Requires-Dist: pytools (==2019.1.1)
Requires-Dist: pycuda (==2019.1.2)
Requires-Dist: torch (==1.2.0)
Requires-Dist: torch-testing (==0.0.2)
Requires-Dist: torchvision (==0.4.0)
Requires-Dist: zensols.actioncli (>=1.0.17)
